{
  "updated_at": "2026-05-30T21:40:58.864Z",
  "member_limit": 2000,
  "selected_group_id": "1075143235",
  "groups": [
    {
      "ok": true,
      "group_id": "1075143235",
      "group_name": "MaaNTE交流群③群",
      "join_url": "http://qm.qq.com/cgi-bin/qm/qr?_wv=1027&k=7Memki8jN3J8qWZc9Wn-kzuAfyBbblZL&authKey=pxFQBJTfblDaWZEDx8I3HPy33eWSMJ%2Fcc%2FTPPOa736jbXAYixBNDjYn9dbF6V%2FgD&noverify=0&group_code=1075143235",
      "member_count": 1886,
      "max_member_count": 2000,
      "joinable": true
    },
    {
      "ok": true,
      "group_id": "1101147419",
      "group_name": "MaaNTE交流群②群",
      "join_url": "http://qm.qq.com/cgi-bin/qm/qr?_wv=1027&k=U7-mz--TZ8VMTTi6o4YxI00EkIYEMp3F&authKey=pG2ofs4koCfHGv5L8ducrxuZumIMJsPiv8WLO1Zx874rsWq3dctl1jztGUcP6glm&noverify=0&group_code=1101147419",
      "member_count": 1934,
      "max_member_count": 2000,
      "joinable": true
    },
    {
      "ok": true,
      "group_id": "1103323319",
      "group_name": "MaaNTE交流群①群",
      "join_url": "http://qm.qq.com/cgi-bin/qm/qr?_wv=1027&k=4KUihTy1OlystyUFOUWKq5wnESzkDWaO&authKey=okTTZxamkJKbdFpDUVYAMCERLlf5oGBa%2FnrgJPQFxNkeEKjFF7dF2fWb7mNDq%2Bno&noverify=0&group_code=1103323319",
      "member_count": 1934,
      "max_member_count": 2000,
      "joinable": true
    },
    {
      "ok": true,
      "group_id": "1106448578",
      "group_name": "MaaNTE交流群⑤群",
      "join_url": "http://qm.qq.com/cgi-bin/qm/qr?_wv=1027&k=M-qimTxioXmX7yPIUHx6PgUkoUh9NDgH&authKey=ke18jGN5KJtSI%2FKUPP06wZUbRKqK278wekoK7SBwu5K2H%2F8cbUXvIpg0ySu8MbBJ&noverify=0&group_code=1106448578",
      "member_count": 2000,
      "max_member_count": 2000,
      "joinable": false
    },
    {
      "ok": true,
      "group_id": "713114598",
      "group_name": "MaaNTE交流群④群",
      "join_url": "http://qm.qq.com/cgi-bin/qm/qr?_wv=1027&k=6jjjXeaEWl144VHKDSbMA0DQYsI-GTGn&authKey=K%2FE52CJbghWcezbG7zra3kMB51xx6Idrb7KlwXZjckKICV8tODzfP7M%2Bg%2FYQL9S%2B&noverify=0&group_code=713114598",
      "member_count": 2000,
      "max_member_count": 2000,
      "joinable": false
    }
  ]
}
